budgeteer/__init__.py
budgeteer/run.py
budgeteer/providers/__init__.py
budgeteer/providers/common_functions.py
budgeteer/providers/config.py
budgeteer/providers/shared_state.py
budgeteer/providers/sqlite_database.py
budgeteer/providers/version.py
budgeteer/providers/http_requests/__init__.py
budgeteer/providers/http_requests/cache_handler.py
budgeteer/providers/http_requests/cloudflare_handlers.py
budgeteer/providers/http_requests/request_handler.py
budgeteer/web_interface/__init__.py
budgeteer/web_interface/web_server.py
budgeteer/web_interface/vuejs_frontend/dist/favicon.ico
budgeteer/web_interface/vuejs_frontend/dist/index.html
budgeteer/web_interface/vuejs_frontend/dist/assets/@formkit-606708a1.js
budgeteer/web_interface/vuejs_frontend/dist/assets/@popperjs-8746c87e.js
budgeteer/web_interface/vuejs_frontend/dist/assets/@vue-de7d3d24.js
budgeteer/web_interface/vuejs_frontend/dist/assets/@vueuse-0fe84a4c.js
budgeteer/web_interface/vuejs_frontend/dist/assets/axios-1df74d48.js
budgeteer/web_interface/vuejs_frontend/dist/assets/bootstrap-39a9ac22.css
budgeteer/web_interface/vuejs_frontend/dist/assets/bootstrap-85852bd1.js
budgeteer/web_interface/vuejs_frontend/dist/assets/bootstrap-icons-999550fa.woff
budgeteer/web_interface/vuejs_frontend/dist/assets/bootstrap-icons-abbba2f8.css
budgeteer/web_interface/vuejs_frontend/dist/assets/bootstrap-icons-cfe45b98.woff2
budgeteer/web_interface/vuejs_frontend/dist/assets/index-d90fbed7.js
budgeteer/web_interface/vuejs_frontend/dist/assets/index-e2d31524.css
budgeteer/web_interface/vuejs_frontend/dist/assets/tippy-a1ae07b3.css
budgeteer/web_interface/vuejs_frontend/dist/assets/vue-4ed993c7.js
budgeteer/web_interface/vuejs_frontend/dist/assets/vue-router-4cd13335.js
budgeteer/web_interface/vuejs_frontend/dist/assets/vue-tippy-7086acf8.js
budgeteer/web_interface/vuejs_frontend/dist/assets/vue-toastification-4522082c.css
budgeteer/web_interface/vuejs_frontend/dist/assets/vue-toastification-6aa87443.js
budgeteer-0.1.8.dist-info/LICENSE.md
budgeteer-0.1.8.dist-info/METADATA
budgeteer-0.1.8.dist-info/WHEEL
budgeteer-0.1.8.dist-info/entry_points.txt
budgeteer-0.1.8.dist-info/top_level.txt
budgeteer-0.1.8.dist-info/RECORD
