Metadata-Version: 2.1
Name: budgeteer
Version: 0.1.8
Summary: Einfacher Überblick über das eigene Budget
Home-page: https://github.com/rix1337/BudgeTeer
Author: rix1337
Author-email: 
License: UNKNOWN
Platform: UNKNOWN
Classifier: Programming Language :: Python :: 3
Classifier: License :: OSI Approved :: MIT License
Classifier: Operating System :: OS Independent
License-File: LICENSE.md
Requires-Dist: bottle (==0.12.25)
Requires-Dist: pycryptodomex (==3.18.0)
